httpx_file/__init__.py
httpx_file/py.typed
httpx_file-0.2.0.dist-info/LICENSE
httpx_file-0.2.0.dist-info/METADATA
httpx_file-0.2.0.dist-info/WHEEL
httpx_file-0.2.0.dist-info/top_level.txt
httpx_file-0.2.0.dist-info/RECORD
